snappiershot/__init__.py
snappiershot/compare.py
snappiershot/config.py
snappiershot/constants.py
snappiershot/errors.py
snappiershot/inspection.py
snappiershot/plugins/__init__.py
snappiershot/plugins/pytest.py
snappiershot/plugins/tracker.py
snappiershot/serializers/__init__.py
snappiershot/serializers/constants.py
snappiershot/serializers/io.py
snappiershot/serializers/json.py
snappiershot/serializers/optional_module_utils.py
snappiershot/serializers/utils.py
snappiershot/snapshot/__init__.py
snappiershot/snapshot/_file.py
snappiershot/snapshot/_raises.py
snappiershot/snapshot/metadata.py
snappiershot/snapshot/snapshot.py
snappiershot/snapshot/status.py
snappiershot-1.1.0.dist-info/entry_points.txt
snappiershot-1.1.0.dist-info/LICENSE
snappiershot-1.1.0.dist-info/WHEEL
snappiershot-1.1.0.dist-info/METADATA
snappiershot-1.1.0.dist-info/RECORD
