Metadata-Version: 2.1
Name: snappiershot
Version: 1.1.0
Summary: Snapshot testing library.
Home-page: https://github.com/MORSECorp/snappiershot
Keywords: snapshot,testing
Author: Ben Bonenfant
Author-email: bonenfan5ben@gmail.com
Requires-Python: >=3.6.2,<4.0.0
Classifier: Development Status :: 4 - Beta
Classifier: Framework :: Pytest
Classifier: Intended Audience :: Developers
Classifier: License :: OSI Approved :: Apache Software License
Classifier: Operating System :: OS Independent
Classifier: Programming Language :: Python :: 3
Classifier: Programming Language :: Python :: 3.10
Classifier: Programming Language :: Python :: 3.7
Classifier: Programming Language :: Python :: 3.8
Classifier: Programming Language :: Python :: 3.9
Classifier: Topic :: Software Development :: Libraries
Classifier: Topic :: Software Development :: Testing :: Unit
Provides-Extra: pandas
Requires-Dist: importlib-metadata (>1.5.1); python_version < "3.8"
Requires-Dist: pandas (>=0.20.0); extra == "pandas"
Requires-Dist: pint (>=0.14,<0.15)
Requires-Dist: pprint_ordered_sets (>=1.0.0,<2.0.0)
Requires-Dist: tomlkit (>=0.7.0,<0.8.0)
Project-URL: Repository, https://github.com/MORSECorp/snappiershot
